LICENSE.md
MANIFEST.in
README.rst
haleasy.py
httest.py
setup.py
HALEasy.egg-info/PKG-INFO
HALEasy.egg-info/SOURCES.txt
HALEasy.egg-info/dependency_links.txt
HALEasy.egg-info/requires.txt
HALEasy.egg-info/top_level.txt
test/test_core.py
test/test_embedded.py
test/test_halhttpclient.py
test/test_haltalk.py
test/test_helpers.py