Metadata-Version: 1.1
Name: HALEasy
Version: 0.4.3
Summary: A HAL client which is very short and simple
Home-page: http://github.com/mattclarkdotnet/haleasy
Author: Matt Clark
Author-email: matt@mattclark.net
License: MIT
Keywords: HAL,json,hypermedia,client
Platform: UNKNOWN
Classifier: Programming Language :: Python
Classifier: Topic :: Software Development :: Libraries :: Python Modules
Classifier: License :: OSI Approved :: MIT License
Classifier: Intended Audience :: Developers
Classifier: Development Status :: 5 - Production/Stable
Classifier: Operating System :: OS Independent
